README.md
setup.cfg
setup.py
st_dataprovider.egg-info/PKG-INFO
st_dataprovider.egg-info/SOURCES.txt
st_dataprovider.egg-info/dependency_links.txt
st_dataprovider.egg-info/requires.txt
st_dataprovider.egg-info/top_level.txt
st_library/__init__.py
st_library/exceptions.py
st_library/library.py
st_library/core/__init__.py
st_library/core/dataprovider/__init__.py
st_library/core/dataprovider/structured_data/__init__.py
st_library/core/dataprovider/structured_data/parser.py
st_library/core/dataprovider/structured_data/schema.py
st_library/core/dataprovider/structured_data/structured_data.py
st_library/core/dataprovider/structured_data/table.py
st_library/core/dataprovider/unstructured_data/__init__.py
st_library/core/dataprovider/unstructured_data/item.py
st_library/core/dataprovider/unstructured_data/unstructured_data.py
st_library/core/logger/__init__.py
st_library/core/logger/logger.py
st_library/core/metadata/__init__.py
st_library/core/metadata/metadata.py
st_library/utils/__init__.py
st_library/utils/api_client/__init__.py
st_library/utils/api_client/api_client.py
st_library/utils/api_client/request.py
st_library/utils/api_client/resource.py
st_library/utils/api_client/models/__init__.py
st_library/utils/api_client/models/script_execution_configuration.py
st_library/utils/api_client/services/__init__.py
st_library/utils/api_client/services/structured_data.py
st_library/utils/api_client/services/unstructured_data.py
st_library/utils/databases/__init__.py
st_library/utils/databases/databases.py
st_library/utils/databases/postgres.py
st_library/utils/databases/redis.py
st_library/utils/generics/__init__.py
st_library/utils/generics/base_object.py
st_library/utils/generics/connectors.py
st_library/utils/generics/singleton.py
st_library/utils/helpers/__init__.py
st_library/utils/helpers/store.py
st_library/utils/shared_toolkit/__init__.py
st_library/utils/shared_toolkit/api_client/__init__.py
st_library/utils/shared_toolkit/api_client/base_api_client.py
st_library/utils/shared_toolkit/api_client/public_key_mixin.py
st_library/utils/shared_toolkit/api_client/resources.py
st_library/utils/shared_toolkit/api_client/sec_access_token_mixin.py
