Metadata-Version: 1.1
Name: st-dataprovider
Version: 1.0.15
Summary: shortest track dataprovider
Home-page: https://github.com/shortesttrack/dataprovider-py
Author: Fugui Xing
Author-email: admin@shortesttrack.com
License: Apache Software License
Download-URL: https://github.com/shortesttrack/dataprovider-py/archive/v1.0.15
Keywords: Shortest Track,st_library,dataprovider
Platform: UNKNOWN
Classifier: Programming Language :: Python :: 2
Classifier: Programming Language :: Python :: 3
Classifier: Environment :: Other Environment
Classifier: Intended Audience :: Developers
Classifier: License :: OSI Approved :: Apache Software License
Classifier: Operating System :: OS Independent
Classifier: Topic :: Software Development :: Libraries :: Python Modules
